[
  {
    "id": 1,
    "name": "Main",
    "path": "UIMain",
    "layer": 0,
    "is_main": false,
    "is_full": false,
    "hiden_other": false,
    "bg_alpha": 0,
    "click_cross": true,
    "click_close": false
  },
  {
    "id": 2,
    "name": "Login",
    "path": "UILogin",
    "layer": 2,
    "is_main": false,
    "is_full": false,
    "hiden_other": true,
    "bg_alpha": 0.5,
    "click_cross": false,
    "click_close": true
  },
  {
    "id": 3,
    "name": "Hero",
    "path": "UIHero",
    "layer": 2,
    "is_main": true,
    "is_full": true,
    "hiden_other": false,
    "bg_alpha": 0,
    "click_cross": false,
    "click_close": false
  },
  {
    "id": 4,
    "name": "Bag",
    "path": "UIBag",
    "layer": 2,
    "is_main": false,
    "is_full": false,
    "hiden_other": false,
    "bg_alpha": 0,
    "click_cross": false,
    "click_close": false
  },
  {
    "id": 5,
    "name": "Shop",
    "path": "UIShop",
    "layer": 2,
    "is_main": false,
    "is_full": true,
    "hiden_other": false,
    "bg_alpha": 0,
    "click_cross": false,
    "click_close": false
  },
  {
    "id": 6,
    "name": "Buy",
    "path": "UIBuy",
    "layer": 3,
    "is_main": false,
    "is_full": false,
    "hiden_other": false,
    "bg_alpha": 0,
    "click_cross": false,
    "click_close": false
  },
  {
    "id": 1000,
    "name": "Loading",
    "path": "UILoading",
    "layer": 5,
    "is_main": false,
    "is_full": false,
    "hiden_other": false,
    "bg_alpha": 0,
    "click_cross": false,
    "click_close": false
  },
  {
    "id": 1001,
    "name": "NetError",
    "path": "UINetError",
    "layer": 7,
    "is_main": false,
    "is_full": false,
    "hiden_other": false,
    "bg_alpha": 0,
    "click_cross": false,
    "click_close": false
  }
]